mockerpy/__init__.py
mockerpy/fake_api.py
mockerpy/fake_api_client.py
mockerpy/fake_node_response.py
mockerpy/fake_stat.py
mockerpy/services/__init__.py
mockerpy/services/responses.py
mockerpy-0.1.0.dist-info/WHEEL
mockerpy-0.1.0.dist-info/METADATA
mockerpy-0.1.0.dist-info/RECORD
