Metadata-Version: 2.1
Name: mockerpy
Version: 0.1.0
Summary: Mock client for Docker-py
License: MIT
Author: Procedural.build
Author-email: admin@procedural.build
Requires-Python: >=3.6,<3.9
Classifier: License :: OSI Approved :: MIT License
Classifier: Programming Language :: Python :: 3
Classifier: Programming Language :: Python :: 3.6
Classifier: Programming Language :: Python :: 3.7
Classifier: Programming Language :: Python :: 3.8
Requires-Dist: docker
